MANIFEST.in
README.md
setup.cfg
setup.py
alertmanager_gchat_integration/__init__.py
alertmanager_gchat_integration/__main__.py
alertmanager_gchat_integration/app.py
alertmanager_gchat_integration/j2_template_engine.py
alertmanager_gchat_integration.egg-info/PKG-INFO
alertmanager_gchat_integration.egg-info/SOURCES.txt
alertmanager_gchat_integration.egg-info/dependency_links.txt
alertmanager_gchat_integration.egg-info/requires.txt
alertmanager_gchat_integration.egg-info/top_level.txt