Metadata-Version: 2.1
Name: alertmanager-gchat-integration
Version: 1.0.1
Summary: The application starts a Web server which logs details of all incoming HTTP requests.
Home-page: https://github.com/julb/alertmanager-gchat-integration
Author: Julb
Author-email: julien@julb.me
License: MIT
Platform: UNKNOWN
Classifier: License :: OSI Approved :: MIT License
Classifier: Programming Language :: Python :: 3
Classifier: Programming Language :: Python :: 3.8
